pymr/__init__.py
pymr/api.py
pymr/bayesian.py
pymr/clumping.py
pymr/harmonize.py
pymr/io.py
pymr/methods.py
pymr/mr.py
pymr/multivariable.py
pymr/plots.py
pymr/sensitivity.py
pymr_genetics-0.1.0.dist-info/METADATA
pymr_genetics-0.1.0.dist-info/WHEEL
pymr_genetics-0.1.0.dist-info/licenses/LICENSE
pymr_genetics-0.1.0.dist-info/RECORD
