Metadata-Version: 2.4
Name: pymr-genetics
Version: 0.1.0
Summary: Modern Python package for Mendelian Randomization analysis
Project-URL: Homepage, https://github.com/maxghenis/pymr
Project-URL: Documentation, https://maxghenis.github.io/pymr
Project-URL: Repository, https://github.com/maxghenis/pymr
Author-email: Max Ghenis <max@policyengine.org>
License-Expression: MIT
License-File: LICENSE
Keywords: causal-inference,epidemiology,genetics,gwas,mendelian-randomization
Classifier: Development Status :: 3 - Alpha
Classifier: Intended Audience :: Science/Research
Classifier: License :: OSI Approved :: MIT License
Classifier: Programming Language :: Python :: 3
Classifier: Programming Language :: Python :: 3.9
Classifier: Programming Language :: Python :: 3.10
Classifier: Programming Language :: Python :: 3.11
Classifier: Programming Language :: Python :: 3.12
Classifier: Topic :: Scientific/Engineering :: Bio-Informatics
Requires-Python: >=3.9
Requires-Dist: matplotlib>=3.5
Requires-Dist: numpy>=1.20
Requires-Dist: pandas>=1.3
Requires-Dist: requests>=2.28
Requires-Dist: scipy>=1.7
Requires-Dist: seaborn>=0.12
Requires-Dist: statsmodels>=0.13
Provides-Extra: dev
Requires-Dist: mypy>=1.0; extra == 'dev'
Requires-Dist: pre-commit>=3.0; extra == 'dev'
Requires-Dist: pytest-cov>=4.0; extra == 'dev'
Requires-Dist: pytest-xdist>=3.0; extra == 'dev'
Requires-Dist: pytest>=7.0; extra == 'dev'
Requires-Dist: ruff>=0.1; extra == 'dev'
Provides-Extra: docs
Requires-Dist: jupyter-book>=1.0; extra == 'docs'
Requires-Dist: myst-nb>=1.0; extra == 'docs'
Requires-Dist: sphinx-autodoc2>=0.5; extra == 'docs'
